llm_git/__init__.py
llm_git/commands.py
llm_git/commit_utils.py
llm_git/config.py
llm_git/config.yaml
llm_git/file_helpers.py
llm_git/git_helpers.py
llm_git/llm_git.py
llm_git/llm_utils.py
llm_git/options.py
llm_git/prompts.py
llm_git/terminal_format.py
llm_git-0.2.2.dist-info/licenses/LICENSE
llm_git-0.2.2.dist-info/METADATA
llm_git-0.2.2.dist-info/WHEEL
llm_git-0.2.2.dist-info/entry_points.txt
llm_git-0.2.2.dist-info/top_level.txt
llm_git-0.2.2.dist-info/RECORD
