Metadata-Version: 2.4
Name: llm-git
Version: 0.2.2
Summary: AI-powered Git commands for the LLM CLI tool
License: Apache-2.0
Project-URL: Homepage, https://github.com/OttoAllmendinger/llm-git
Project-URL: Repository, https://github.com/OttoAllmendinger/llm-git
Requires-Python: >=3.9
License-File: LICENSE
Requires-Dist: llm
Requires-Dist: click
Requires-Dist: deepmerge
Requires-Dist: pyyaml
Requires-Dist: rich
Requires-Dist: pygments
Provides-Extra: test
Requires-Dist: pytest; extra == "test"
Requires-Dist: pytest-cov; extra == "test"
Provides-Extra: dev
Requires-Dist: ruff; extra == "dev"
Dynamic: license-file
